localbot/__main__.py
localbot/cli_args.py
localbot/event_handler.py
localbot/resource_reporting.py
localbot/runtime_manager.py
localbot/config/__init__.py
localbot/config/schema.py
localbot-1.0.0.dist-info/METADATA
localbot-1.0.0.dist-info/WHEEL
localbot-1.0.0.dist-info/RECORD
