Metadata-Version: 2.4
Name: localbot
Version: 1.0.0
Requires-Python: >=3.12
Requires-Dist: mirmod
Requires-Dist: ulid2
